braid_formula/__init__.py
braid_formula/cli.py
braid_formula/core.py
braid_formula/exceptions.py
braid_formula/models.py
braid_formula-0.1.1.dist-info/licenses/LICENSE
braid_formula-0.1.1.dist-info/METADATA
braid_formula-0.1.1.dist-info/WHEEL
braid_formula-0.1.1.dist-info/entry_points.txt
braid_formula-0.1.1.dist-info/top_level.txt
braid_formula-0.1.1.dist-info/RECORD
