Metadata-Version: 2.4
Name: braid-formula
Version: 0.1.1
Summary: A settlement engine for collaborative projects. Calculate fair payouts when multiple people collaborate with shared revenue and individual expenses.
Author-email: The Bloc Foundation <hello@theblocfoundation.org>
Maintainer: J. Sims
License: MIT
Project-URL: Homepage, https://github.com/afrotech-panther/braid-formula
Project-URL: Documentation, https://github.com/afrotech-panther/braid-formula#readme
Project-URL: Repository, https://github.com/afrotech-panther/braid-formula.git
Project-URL: Issues, https://github.com/afrotech-panther/braid-formula/issues
Project-URL: Changelog, https://github.com/afrotech-panther/braid-formula/blob/main/CHANGELOG.md
Keywords: settlement,profit-sharing,expense-splitting,collaboration,revenue,payout,calculator,formula,braid
Classifier: Development Status :: 4 - Beta
Classifier: Intended Audience :: Developers
Classifier: Intended Audience :: Financial and Insurance Industry
Classifier: License :: OSI Approved :: MIT License
Classifier: Operating System :: OS Independent
Classifier: Programming Language :: Python :: 3
Classifier: Programming Language :: Python :: 3.9
Classifier: Programming Language :: Python :: 3.10
Classifier: Programming Language :: Python :: 3.11
Classifier: Programming Language :: Python :: 3.12
Classifier: Topic :: Office/Business :: Financial :: Accounting
Classifier: Topic :: Software Development :: Libraries :: Python Modules
Classifier: Typing :: Typed
Requires-Python: >=3.9
License-File: LICENSE
Provides-Extra: dev
Requires-Dist: pytest>=7.0; extra == "dev"
Requires-Dist: pytest-cov>=4.0; extra == "dev"
Requires-Dist: black>=23.0; extra == "dev"
Requires-Dist: mypy>=1.0; extra == "dev"
Requires-Dist: ruff>=0.1; extra == "dev"
Dynamic: license-file
